{
  "items": [
    {
      "type": "group",
      "ctime": 1718933748044,
      "items": [
        {
          "type": "group",
          "ctime": 1718936279855,
          "items": [
            {
              "type": "file",
              "ctime": 1719360687621,
              "path": "PROJECT/TODO LIST.md",
              "subpath": "#^-"
            },
            {
              "type": "group",
              "ctime": 1718947020408,
              "items": [
                {
                  "type": "group",
                  "ctime": 1718947056473,
                  "items": [],
                  "title": "WEKLEY"
                }
              ],
              "title": "2024"
            },
            {
              "type": "group",
              "ctime": 1718947020408,
              "items": [],
              "title": "GRAPHICS"
            },
            {
              "type": "group",
              "ctime": 1720140145011,
              "items": [
                {
                  "type": "file",
                  "ctime": 1720140282502,
                  "path": "PROJECT/STUDY/GRAPHICS & NETWORKS 학습.md",
                  "subpath": "#^-"
                },
                {
                  "type": "group",
                  "ctime": 1720140145011,
                  "items": [],
                  "title": "WebGL2"
                },
                {
                  "type": "file",
                  "ctime": 1720140145011,
                  "path": "PROJECT/STUDY/Tutorial 01.md",
                  "subpath": "#^-"
                }
              ],
              "title": "STUDY"
            }
          ],
          "title": "PROJECT"
        },
        {
          "type": "group",
          "ctime": 1718936279855,
          "items": [],
          "title": "AREA"
        },
        {
          "type": "group",
          "ctime": 1718936279855,
          "items": [],
          "title": "RESOURCE"
        },
        {
          "type": "group",
          "ctime": 1718936279855,
          "items": [
            {
              "type": "group",
              "ctime": 1719793994686,
              "items": [
                {
                  "type": "file",
                  "ctime": 1719794008048,
                  "path": "ARCHIVE/Annual Notes/2024 Year.md",
                  "subpath": "#^-"
                },
                {
                  "type": "group",
                  "ctime": 1719794008048,
                  "items": [],
                  "title": "2024.06"
                },
                {
                  "type": "group",
                  "ctime": 1719794008048,
                  "items": [],
                  "title": "2024.06"
                }
              ],
              "title": "Annual Notes"
            },
            {
              "type": "group",
              "ctime": 1719793994686,
              "items": [],
              "title": "DIGITAL TWIN"
            },
            {
              "type": "file",
              "ctime": 1719793994686,
              "path": "ARCHIVE/NVIDIA DRIVE AGX.md",
              "subpath": "#^-"
            },
            {
              "type": "file",
              "ctime": 1719793994686,
              "path": "ARCHIVE/TEMP FILE.md",
              "subpath": "#^-"
            }
          ],
          "title": "ARCHIVE"
        },
        {
          "type": "group",
          "ctime": 1718936279855,
          "items": [],
          "title": "GARAGE"
        }
      ],
      "title": "sortspec"
    }
  ]
}